flora_utils_py/__init__.py
flora_utils_py/exceptions.py
flora_utils_py-0.1.2.dist-info/LICENSE
flora_utils_py-0.1.2.dist-info/METADATA
flora_utils_py-0.1.2.dist-info/WHEEL
flora_utils_py-0.1.2.dist-info/RECORD
