Metadata-Version: 2.1
Name: flora-utils-py
Version: 0.1.2
Summary: Awesome `flora-utils-py` is a Python cli/package created with https://github.com/TezRomacH/python-package-template
Home-page: https://github.com/Flora/flora-utils-py
License: Apache Software License 2.0
Author: Flora
Author-email: tiencheng@flora.so
Requires-Python: >=3.7,<4.0
Classifier: Development Status :: 3 - Alpha
Classifier: Intended Audience :: Developers
Classifier: License :: OSI Approved :: Apache Software License
Classifier: License :: Other/Proprietary License
Classifier: Operating System :: OS Independent
Classifier: Programming Language :: Python :: 3
Classifier: Programming Language :: Python :: 3.7
Classifier: Programming Language :: Python :: 3.8
Classifier: Programming Language :: Python :: 3.9
Classifier: Programming Language :: Python :: 3.10
Classifier: Programming Language :: Python :: 3.11
Classifier: Topic :: Software Development :: Libraries :: Python Modules
Requires-Dist: importlib_metadata (>=4.5.0,<5.0.0) ; python_version < "3.8"
Project-URL: Repository, https://github.com/Flora/flora-utils-py
